numba_aot_compiler/LICENSE
numba_aot_compiler/README.md
numba_aot_compiler/__init__.py
numba_aot_compiler/requirements.txt
numba_aot_compiler/thirdparty.json
numba_aot_compiler-0.14.dist-info/LICENSE.rst
numba_aot_compiler-0.14.dist-info/METADATA
numba_aot_compiler-0.14.dist-info/WHEEL
numba_aot_compiler-0.14.dist-info/top_level.txt
numba_aot_compiler-0.14.dist-info/RECORD
