Metadata-Version: 2.1
Name: numba-aot-compiler
Version: 0.14
Summary: A function to facilitate the Ahead-of-time compilation with Numba
Home-page: https://github.com/hansalemaos/numba_aot_compiler
Author: Johannes Fischer
Author-email: <aulasparticularesdealemaosp@gmail.com>
License: MIT
Keywords: numba,aot,compile
Classifier: Development Status :: 4 - Beta
Classifier: Programming Language :: Python :: 3 :: Only
Classifier: Programming Language :: Python :: 3.10
Classifier: Topic :: Scientific/Engineering :: Visualization
Classifier: Topic :: Software Development :: Libraries :: Python Modules
Classifier: Topic :: Utilities
License-File: LICENSE.rst
Requires-Dist: deepcopyall
Requires-Dist: numba
Requires-Dist: ordered-set
Requires-Dist: touchtouch
